{
  "animateLoading": true,
  "backgroundColor": "#FFFFFF",
  "borderColor": "#E0DEDE",
  "borderRadius": "{{appsmith.theme.borderRadius.appBorderRadius}}",
  "borderWidth": "1",
  "bottomRow": 78,
  "boxShadow": "{{appsmith.theme.boxShadow.appBoxShadow}}",
  "children": [
    {
      "borderRadius": "{{appsmith.theme.borderRadius.appBorderRadius}}",
      "bottomRow": 390,
      "boxShadow": "{{appsmith.theme.boxShadow.appBoxShadow}}",
      "canExtend": false,
      "containerStyle": "none",
      "detachFromLayout": true,
      "dynamicBindingPathList": [
        {
          "key": "borderRadius"
        },
        {
          "key": "boxShadow"
        }
      ],
      "dynamicHeight": "AUTO_HEIGHT",
      "flexLayers": [],
      "isLoading": false,
      "isVisible": true,
      "key": "s2pu0lhtn8",
      "leftColumn": 0,
      "maxDynamicHeight": 9000,
      "minDynamicHeight": 4,
      "minHeight": 400,
      "minWidth": 450,
      "mobileBottomRow": 400,
      "mobileLeftColumn": 0,
      "mobileRightColumn": 412.5625,
      "mobileTopRow": 0,
      "needsErrorInfo": false,
      "parentColumnSpace": 1,
      "parentId": "s5g8uw2bs5",
      "parentRowSpace": 1,
      "renderMode": "CANVAS",
      "responsiveBehavior": "fill",
      "rightColumn": 412.5625,
      "topRow": 0,
      "type": "CANVAS_WIDGET",
      "version": 1,
      "widgetId": "smyp911k6q",
      "widgetName": "Canvas1"
    }
  ],
  "dynamicBindingPathList": [
    {
      "key": "borderRadius"
    },
    {
      "key": "boxShadow"
    }
  ],
  "dynamicHeight": "AUTO_HEIGHT",
  "flexVerticalAlignment": "stretch",
  "isCanvas": true,
  "isLoading": false,
  "isVisible": true,
  "key": "iotfw35mfh",
  "leftColumn": 0,
  "maxDynamicHeight": 9000,
  "minDynamicHeight": 10,
  "minWidth": 450,
  "mobileBottomRow": 79,
  "mobileLeftColumn": 0,
  "mobileRightColumn": 23,
  "mobileTopRow": 39,
  "needsErrorInfo": false,
  "originalBottomRow": 79,
  "originalTopRow": 39,
  "parentColumnSpace": 17.9375,
  "parentId": "0",
  "parentRowSpace": 10,
  "positioning": "fixed",
  "renderMode": "CANVAS",
  "responsiveBehavior": "fill",
  "rightColumn": 23,
  "shouldScrollContents": true,
  "topRow": 39,
  "type": "FORM_WIDGET",
  "widgetId": "s5g8uw2bs5",
  "widgetName": "Form1"
}