{
    "boxShadow": "none",
    "widgetName": "Container10",
    "borderColor": "transparent",
    "isCanvas": true,
    "displayName": "Container",
    "iconSVG": "/static/media/icon.1977dca3370505e2db3a8e44cfd54907.svg",
    "searchTags": [
        "div",
        "parent",
        "group"
    ],
    "topRow": 32,
    "bottomRow": 47,
    "parentRowSpace": 10,
    "type": "CONTAINER_WIDGET",
    "hideCard": false,
    "shouldScrollContents": true,
    "animateLoading": true,
    "parentColumnSpace": 12.5416015625,
    "dynamicTriggerPathList": [],
    "leftColumn": 0,
    "dynamicBindingPathList": [{"key": "borderRadius"}],
    "children": [{
        "widgetName": "Canvas23",
        "isDeprecated": false,
        "rightColumn": 300.9984375,
        "detachFromLayout": true,
        "displayName": "Canvas",
        "widgetId": "8xtrb6007u",
        "topRow": 0,
        "bottomRow": 150,
        "containerStyle": "none",
        "parentRowSpace": 1,
        "isVisible": true,
        "type": "CANVAS_WIDGET",
        "canExtend": false,
        "version": 1,
        "hideCard": true,
        "parentId": "28h3qpb9jq",
        "minHeight": 150,
        "renderMode": "CANVAS",
        "isLoading": false,
        "parentColumnSpace": 1,
        "leftColumn": 0,
        "dynamicBindingPathList": [],
        "key": "e1ez6lj0em"
    }],
    "borderWidth": "1",
    "key": "yo5wkorhut",
    "backgroundColor": "#F2F4F8",
    "isDeprecated": false,
    "rightColumn": 64,
    "dynamicHeight": "FIXED",
    "widgetId": "28h3qpb9jq",
    "containerStyle": "card",
    "isVisible": true,
    "version": 1,
    "parentId": "gmnogpzoje",
    "renderMode": "CANVAS",
    "isLoading": false,
    "borderRadius": "{{appsmith.theme.borderRadius.appBorderRadius}}",
    "maxDynamicHeight": 9000,
    "minDynamicHeight": 10
}