{
  "allowedFileTypes": [],
  "animateLoading": true,
  "borderRadius": "{{appsmith.theme.borderRadius.appBorderRadius}}",
  "bottomRow": 10,
  "boxShadow": "none",
  "buttonColor": "{{appsmith.theme.colors.primaryColor}}",
  "displayName": "FilePicker",
  "dynamicBindingPathList": [
    {
      "key": "buttonColor"
    },
    {
      "key": "borderRadius"
    }
  ],
  "dynamicTriggerPathList": [],
  "dynamicTyping": true,
  "fileDataType": "Base64",
  "files": [],
  "hideCard": false,
  "iconSVG": "/static/media/icon.7c5ad9c357928c6ff5701bf51a56c2e5.svg",
  "isDefaultClickDisabled": true,
  "isDeprecated": false,
  "isDisabled": false,
  "isLoading": false,
  "isRequired": false,
  "isVisible": true,
  "key": "a0920u8ow1",
  "label": "Upload Files",
  "leftColumn": 26,
  "maxFileSize": 5,
  "maxNumFiles": 1,
  "parentColumnSpace": 12.5416015625,
  "parentId": "8xtrb6007u",
  "parentRowSpace": 10,
  "renderMode": "CANVAS",
  "rightColumn": 38,
  "searchTags": [
    "upload"
  ],
  "selectedFiles": [],
  "topRow": 6,
  "type": "FILE_PICKER_WIDGET_V2",
  "version": 1,
  "widgetId": "73xt8dmybb",
  "widgetName": "FilePicker1"
}